{
  "2": [
    {
      "color": "Red And White",
      "description": "In Celebration of FC Bayern Munich's Historic Season"
    },
    {
      "color": "Blue And Orange",
      "description": "In Celebration of the New York Knicks' NBA Home Playoff Game"
    }
  ],
  "4": [
    {
      "color": "Orange",
      "description": "In Partnership with Everytown for Gun Safety Support Fund in honor of National Gun Violence Awareness Day"
    }
  ],
  "13": [
    {
      "color": "Purple And Gold",
      "description": "In Honor of the Westminster Kennel Club Dog Show"
    }
  ],
  "17": [
    {
      "color": "Red, White And Blue",
      "description": "7:30 pm - 10:00 pm: TV Shoot"
    }
  ]
}