{
  "12": [
    {
      "color": "Red, White And Blue Sparkle",
      "description": "To Welcome Home the Athletes Who Competed in the Games in Tokyo"
    }
  ],
  "15": [
    {
      "color": "Green, White And Orange",
      "description": "In Celebration of India Day"
    }
  ],
  "18": [
    {
      "color": "Green",
      "description": "In Honor of the PGA Tour's Northern Trust Tournament"
    }
  ],
  "19": [
    {
      "color": "Purple",
      "description": "In Partnership with the International Paralympic Committee in Honor of WeThe15 Campaign"
    }
  ]
}