{
  "2": [
    {
      "color": "Red, White And Blue",
      "description": "In Celebration of Fourth of July"
    }
  ],
  "3": [
    {
      "color": "Red, White And Blue",
      "description": "In Celebration of Fourth of July"
    }
  ],
  "4": [
    {
      "color": "Red, White And Blue",
      "description": "In Celebration of Fourth of July"
    }
  ],
  "10": [
    {
      "color": "Gold, Black And Aquamarine",
      "description": "In Partnership with The Bahamas Consulate General in New York to Celebrate the 50th Anniversary of Independence"
    }
  ],
  "14": [
    {
      "color": "Blue, White And Red",
      "description": "In Partnership with The Consulate General of France in New York in Celebration of Bastille Day"
    }
  ],
  "15": [
    {
      "color": "White, Green And Purple",
      "description": "In Celebration of the Wimbledon Championship"
    }
  ],
  "16": [
    {
      "color": "Tie Dye",
      "description": "In Honor of Dead & Company\u2019s Final Show"
    }
  ],
  "18": [
    {
      "color": "Yellow, Blue And Red",
      "description": "In Partnership with Expedia Group in Celebration of the Launch of One Key"
    }
  ],
  "20": [
    {
      "color": "Red, Blue And Yellow",
      "description": "In Partnership with the Consulate General of Colombia in New York in Celebration of Colombian Independence Day"
    }
  ],
  "26": [
    {
      "color": "Split Lights: Blue And White Pinstripes For The New York Yankees And Orange And Blue For The New York Mets",
      "description": "In Honor of the New York City Subway Series"
    }
  ]
}